[
  {
    "id": 315162,
    "title": "Puss in Boots: The Last Wish",
    "release_date": "2022-12-21",
    "backdrop_path": "/r9PkFnRUIthgBp2JZZzD380MWZy.jpg"
  },
  {
    "id": 877269,
    "title": "Strange World",
    "release_date": "2022-11-23",
    "backdrop_path": "/5wDBVictj4wUYZ31gR5WzCM9dLD.jpg"
  },
  {
    "id": 555604,
    "title": "Guillermo del Toro's Pinocchio",
    "release_date": "2022-11-18",
    "backdrop_path": "/2JeIqOdSM5nC1SQmuhUOfj3iB1U.jpg"
  },
  {
    "id": 573171,
    "title": "A Frozen Rooster",
    "release_date": "2022-12-14",
    "backdrop_path": "/qdFrqXYH6PtyAVlegub7bpoSgro.jpg"
  },
  {
    "id": 1045944,
    "title": "The Boss Baby: Christmas Bonus",
    "release_date": "2022-12-06",
    "backdrop_path": "/nITzFbM1JS7WEvFjjGL0kCb2yPr.jpg"
  },
  {
    "id": 751741,
    "title": "Night at the Museum: Kahmunrah Rises Again",
    "release_date": "2022-12-09",
    "backdrop_path": "/6rax7iv5yQtldc3ApEvrheJf8uw.jpg"
  },
  {
    "id": 417859,
    "title": "Puss in Boots",
    "release_date": "2011-10-27",
    "backdrop_path": "/eSdpZZQubPSZ47qppFfUPbKsWlw.jpg"
  },
  {
    "id": 438695,
    "title": "Sing 2",
    "release_date": "2021-12-01",
    "backdrop_path": "/6mJrgL7Mi13XjJeGYJFlD6UEVQw.jpg"
  },
  {
    "id": 635302,
    "title": "Demon Slayer -Kimetsu no Yaiba- The Movie: Mugen Train",
    "release_date": "2020-10-16",
    "backdrop_path": "/qjGrUmKW78MCFG8PTLDBp67S27p.jpg"
  },
  {
    "id": 610150,
    "title": "Dragon Ball Super: Super Hero",
    "release_date": "2022-06-11",
    "backdrop_path": "/uR0FopHrAjDlG5q6PZB07a1JOva.jpg"
  },
  {
    "id": 897192,
    "title": "Diary of a Wimpy Kid: Rodrick Rules",
    "release_date": "2022-12-02",
    "backdrop_path": "/94QHrTXnxdmIyXWGUpOPe7PU8DL.jpg"
  },
  {
    "id": 1018403,
    "title": "Tom and Jerry Snowman's Land",
    "release_date": "2022-09-06",
    "backdrop_path": "/oqwqnaaoSpQMqAQyoEiF8W2F7Id.jpg"
  },
  {
    "id": 568124,
    "title": "Encanto",
    "release_date": "2021-10-13",
    "backdrop_path": "/3G1Q5xF40HkUBJXxt2DQgQzKTp5.jpg"
  },
  {
    "id": 438148,
    "title": "Minions: The Rise of Gru",
    "release_date": "2022-06-29",
    "backdrop_path": "/bn3fAIckhOFEnrIZNCSbgHXRHLY.jpg"
  },
  {
    "id": 1001865,
    "title": "Scrooge: A Christmas Carol",
    "release_date": "2022-11-18",
    "backdrop_path": "/wMNY6tU9WOUeAMRfqbCYwceOl9u.jpg"
  },
  {
    "id": 939210,
    "title": "Blue's Big City Adventure",
    "release_date": "2022-11-18",
    "backdrop_path": "/17sIiv4LGapYnyvdpKxA1vozBqY.jpg"
  },
  {
    "id": 585511,
    "title": "Luck",
    "release_date": "2022-08-05",
    "backdrop_path": "/3VQj6m0I6gkuRaljmhNZl0XR3by.jpg"
  },
  {
    "id": 508947,
    "title": "Turning Red",
    "release_date": "2022-03-10",
    "backdrop_path": "/fOy2Jurz9k6RnJnMUMRDAgBwru2.jpg"
  },
  {
    "id": 1037858,
    "title": "The Soccer Football Movie",
    "release_date": "2022-11-09",
    "backdrop_path": "/sqVxhRkPwOo6jogWZjE99V1HRE1.jpg"
  },
  {
    "id": 676701,
    "title": "Tad, the Lost Explorer and the Emerald Tablet",
    "release_date": "2022-08-24",
    "backdrop_path": "/d5aiAn1tTH2VHVPSTIKfWoICwCh.jpg"
  }
]
